transcriptionary/__init__.py
transcriptionary/axes.py
transcriptionary/colors.py
transcriptionary/get_coords.py
transcriptionary/glyphs.py
transcriptionary/process_gene_gff.py
transcriptionary/project_coords.py
transcriptionary/transcriptionary.py
transcriptionary/widget_callbacks.py
transcriptionary-0.1.1.dist-info/LICENSE
transcriptionary-0.1.1.dist-info/METADATA
transcriptionary-0.1.1.dist-info/WHEEL
transcriptionary-0.1.1.dist-info/entry_points.txt
transcriptionary-0.1.1.dist-info/top_level.txt
transcriptionary-0.1.1.dist-info/RECORD
